LICENSE
README.md
pyproject.toml
setup.cfg
setup.py
src/spagrn/__init__.py
src/spagrn/auprc.py
src/spagrn/autocor.py
src/spagrn/c_autocor.py
src/spagrn/corexp.py
src/spagrn/g_autocor.py
src/spagrn/m_autocor.py
src/spagrn/network.py
src/spagrn/plot.py
src/spagrn/regulatory_network.py
src/spagrn/results.py
src/spagrn/simulator.py
src/spagrn/spa_logger.py
src/spagrn.egg-info/PKG-INFO
src/spagrn.egg-info/SOURCES.txt
src/spagrn.egg-info/dependency_links.txt
src/spagrn.egg-info/entry_points.txt
src/spagrn.egg-info/requires.txt
src/spagrn.egg-info/top_level.txt
src/spagrn/cli/__init__.py
src/spagrn/cli/spagrn_parser.py