Metadata-Version: 2.1
Name: spagrn
Version: 1.1.4
Summary: A comprehensive tool to infer TF-centred, spatial gene regulatory networks for the spatially resolved transcriptomic data.
Home-page: https://github.com/BGI-Qingdao/SpaGRN
Author: Yao LI
Author-email: Yao LI <liyao1@genomics.cn>
Platform: any
Classifier: Programming Language :: Python :: 3
Classifier: License :: OSI Approved :: GNU General Public License v3 or later (GPLv3+)
Classifier: Operating System :: OS Independent
Requires-Python: >=3.8,<3.9
License-File: LICENSE
